eventIsotropy/__init__.py
eventIsotropy/cylGen.py
eventIsotropy/emdVar.py
eventIsotropy/spherGen.py
eventIsotropy-0.0.1.dist-info/LICENSE
eventIsotropy-0.0.1.dist-info/METADATA
eventIsotropy-0.0.1.dist-info/WHEEL
eventIsotropy-0.0.1.dist-info/top_level.txt
eventIsotropy-0.0.1.dist-info/RECORD
