Metadata-Version: 2.1
Name: eventIsotropy
Version: 0.0.1
Summary: a robust measure of event isotropy at colliders 
Home-page: https://github.com/caricesarotti/event_isotropy
Author: Cari Cesarotti
License: MIT
Classifier: Development Status :: 2 - Pre-Alpha
Classifier: Programming Language :: Python :: 3.6
Classifier: Programming Language :: Python :: 3.7
Classifier: Programming Language :: Python :: 3.8
Classifier: License :: OSI Approved :: MIT License
Classifier: Topic :: Scientific/Engineering
Classifier: Topic :: Scientific/Engineering :: Physics
Requires-Python: >=3.6
License-File: LICENSE
Requires-Dist: POT
Requires-Dist: astropy-healpix
Provides-Extra: test
Requires-Dist: matplotlib ; extra == 'test'
Requires-Dist: prettytable ; extra == 'test'
